autodiff/__init__.py
autodiff/forward/__init__.py
autodiff/forward/dual.py
autodiff/forward/operations.py
autodiff/reverse/__init__.py
autodiff/reverse/node.py
autodiff/reverse/operations.py
ac207_autodiff-0.1.0.dist-info/METADATA
ac207_autodiff-0.1.0.dist-info/WHEEL
ac207_autodiff-0.1.0.dist-info/top_level.txt
ac207_autodiff-0.1.0.dist-info/RECORD
