Metadata-Version: 2.1
Name: ac207-autodiff
Version: 0.1.0
Summary: An automatic differentiation package.
Home-page: https://github.com/cs107-XKVH/cs107-FinalProject
Author: Xuliang Guo, Kamran Ahmed, Van Anh Le, Hanwen Cui
License: UNKNOWN
Platform: UNKNOWN
Classifier: Intended Audience :: Developers
Classifier: Programming Language :: Python :: 3
Classifier: Topic :: Software Development :: Libraries :: Python Modules
Requires-Python: >=3.8
Requires-Dist: numpy (>=1.21.4)
